LICENSE
MANIFEST.in
README.md
setup.py
proxies_taster/__init__.py
proxies_taster/__main__.py
proxies_taster/events_data.py
proxies_taster/exceptions.py
proxies_taster/proxies_parser_logger.py
proxies_taster/taster.py
proxies_taster/types.py
proxies_taster.egg-info/PKG-INFO
proxies_taster.egg-info/SOURCES.txt
proxies_taster.egg-info/dependency_links.txt
proxies_taster.egg-info/entry_points.txt
proxies_taster.egg-info/requires.txt
proxies_taster.egg-info/top_level.txt