Metadata-Version: 2.1
Name: proxies-taster
Version: 1.2.4
Summary: Пакет для проверки прокси
Home-page: https://github.com/TheWhatis/ProxiesTaster
Download-URL: https://github.com/TheWhatis/ProxiesTaster/dist/proxies-taster-1.2.4.zip
Author: Whatis
Author-email: asdwdagwahwabe@gmail.com
License: GPL
Platform: any
License-File: LICENSE
Requires-Dist: aiohttp
Requires-Dist: aiohttp-proxy
Requires-Dist: fake-useragent
Requires-Dist: PyEventEmitter
